{
	"status":1,
	"message":"success",
	"data":[
		{"id":41, "title":"hurom/惠人原汁机 HU7WN3L新三代家用全自动榨汁机果汁机原装", "img":"/img/images-index/220_201711141457563070250.jpg", "price":3980.00},
		{"id":42, "title":"Coway 厨下式 五级过滤净水器 直饮机 反渗透 P-09CR", "img":"/img/images-index/220_201711281308346847310.jpg", "price":2880.00},
		{"id":43, "title":"美的(Midea)台式迷你饮水机MYR720T家用办公制热温热型", "img":"/img/images-index/220_201711281018242015970.jpg", "price":129.00},
		{"id":44, "title":"美的（Midea） 电压力锅MY-PCS5036P双胆智能5L多功能家用", "img":"/img/images-index/220_201711281004358869420.jpg", "price":419.00},
		{"id":45, "title":"美的(Midea)电饭煲HS4010 IH立体加热 沸腾焖香阀 精钢鼎釜4L电", "img":"/img/images-index/220_201711280959263667980.jpg", "price":859.00}
		
	]
}